[
  {
    "mPageSize" : "128",
    "mPagesPerBlock" : "4",
    "mTotalPages" : "1024",
    "mMaxReadRetries" : "1",
    "mRandomSeed" : "4",
    "mMaxPageEraseCount": "5",
    "dataServerId" : "1",
    "cacheSize" : "0",
    "mDisturbanceCyclesExponent" : "3",
    "mDisturbanceReadsExponent" : "1",
    "mDataScrubbingThreshold"  : "0.1"
  },
  {
    "mPageSize" : "128",
    "mPagesPerBlock" : "4",
    "mTotalPages" : "1024",
    "mMaxReadRetries" : "1",
    "mRandomSeed" : "4",
    "mMaxPageEraseCount": "5",
    "dataServerId" : "2",
    "cacheSize" : "0",
    "mDisturbanceCyclesExponent" : "3",
    "mDisturbanceReadsExponent" : "1",
    "mDataScrubbingThreshold"  : "0.1"
  },
  {
    "mPageSize" : "128",
    "mPagesPerBlock" : "4",
    "mTotalPages" : "1024",
    "mMaxReadRetries" : "1",
    "mRandomSeed" : "4",
    "mMaxPageEraseCount": "5",
    "dataServerId" : "3",
    "cacheSize" : "0",
    "mDisturbanceCyclesExponent" : "3",
    "mDisturbanceReadsExponent" : "1",
    "mDataScrubbingThreshold"  : "0.1"
  }
]
